toonpy/__init__.py
toonpy/api.py
toonpy/cli.py
toonpy/errors.py
toonpy/parallel.py
toonpy/parser.py
toonpy/serializer.py
toonpy/utils.py
toontools-0.2.0.dist-info/licenses/LICENSE
toontools-0.2.0.dist-info/METADATA
toontools-0.2.0.dist-info/WHEEL
toontools-0.2.0.dist-info/entry_points.txt
toontools-0.2.0.dist-info/top_level.txt
toontools-0.2.0.dist-info/RECORD
