Metadata-Version: 2.4
Name: toontools
Version: 0.2.0
Summary: Conversion utilities between JSON and TOON (Token-Oriented Object Notation)
Author-email: shinjidev <palomares.c@gmail.com>
License-Expression: MIT
Project-URL: Homepage, https://github.com/shinjidev/toonpy
Project-URL: Repository, https://github.com/shinjidev/toonpy
Project-URL: Documentation, https://github.com/shinjidev/toonpy#readme
Project-URL: Bug Tracker, https://github.com/shinjidev/toonpy/issues
Keywords: toon,json,serialization,parser
Classifier: Development Status :: 4 - Beta
Classifier: Intended Audience :: Developers
Classifier: Programming Language :: Python
Classifier: Programming Language :: Python :: 3
Classifier: Programming Language :: Python :: 3 :: Only
Classifier: Programming Language :: Python :: 3.9
Classifier: Programming Language :: Python :: 3.10
Classifier: Programming Language :: Python :: 3.11
Classifier: Programming Language :: Python :: 3.12
Classifier: Topic :: Software Development :: Libraries
Classifier: Topic :: Utilities
Requires-Python: >=3.9
License-File: LICENSE
Provides-Extra: tests
Requires-Dist: pytest>=7; extra == "tests"
Requires-Dist: hypothesis>=6; extra == "tests"
Requires-Dist: coverage>=7; extra == "tests"
Provides-Extra: examples
Requires-Dist: tiktoken>=0.5.2; extra == "examples"
Dynamic: license-file
